{"fset-735":"en/fs/et/-7/en-fset-735.html","fset-736":"en/fs/et/-7/en-fset-736.html","fset-734":"en/fs/et/-7/en-fset-734.html","faa-220":"en/fa/a-/22/en-faa-220.html","faa-218":"en/fa/a-/21/en-faa-218.html","faa-219":"en/fa/a-/21/en-faa-219.html","finh-050":"en/fi/nh/-0/en-finh-050.html","fstb-002":"en/fs/tb/-0/en-fstb-002.html","fskt-033":"en/fs/kt/-0/en-fskt-033.html","fstd-003":"en/fs/td/-0/en-fstd-003.html","fsta-005":"en/fs/ta/-0/en-fsta-005.html","fstd-002":"en/fs/td/-0/en-fstd-002.html","fstb-003":"en/fs/tb/-0/en-fstb-003.html","fiv-006":"en/fi/v-/00/en-fiv-006.html","fste-003":"en/fs/te/-0/en-fste-003.html","fset-732":"en/fs/et/-7/en-fset-732.html","fset-733":"en/fs/et/-7/en-fset-733.html","fset-731":"en/fs/et/-7/en-fset-731.html","faa-217":"en/fa/a-/21/en-faa-217.html","faa-216":"en/fa/a-/21/en-faa-216.html","faa-215":"en/fa/a-/21/en-faa-215.html","fcdc-092":"en/fc/dc/-0/en-fcdc-092.html","flav-180":"en/fl/av/-1/en-flav-180.html","fiv-005":"en/fi/v-/00/en-fiv-005.html","fnk-035":"en/fn/k-/03/en-fnk-035.html","fsg-016":"en/fs/g-/01/en-fsg-016.html","fnk-034":"en/fn/k-/03/en-fnk-034.html","fnk-033":"en/fn/k-/03/en-fnk-033.html","fstd-001":"en/fs/td/-0/en-fstd-001.html","fstb-001":"en/fs/tb/-0/en-fstb-001.html","fstc-003":"en/fs/tc/-0/en-fstc-003.html","fste-002":"en/fs/te/-0/en-fste-002.html"}